MANIFEST.in
README.md
README.rst
requirements.txt
setup.py
theeasytype.py
theeasytype.egg-info/PKG-INFO
theeasytype.egg-info/SOURCES.txt
theeasytype.egg-info/dependency_links.txt
theeasytype.egg-info/top_level.txt