Metadata-Version: 1.0
Name: theeasytype
Version: 0.0.1
Summary: `the` assert basic type
Home-page: https://github.com/the-py/the-easytype
Author: Yan Wenjun
Author-email: mylastnameisyan@gmail.com
License: MIT
Platform: UNKNOWN
Classifier: License :: OSI Approved :: MIT License
Classifier: Topic :: Software Development :: Libraries
